{"textures":{"0":"modelengine:entity/mso_snakewarrior1"},"elements":[{"from":[7.4998,7.366667,-7.4562387],"to":[8.4998,8.366667,11.543761],"faces":{"east":{"uv":[6.25,0.0,8.625,0.125],"tintindex":0,"rotation":0,"texture":"#0"},"south":{"uv":[8.75,8.75,8.875,8.875],"tintindex":0,"rotation":0,"texture":"#0"},"north":{"uv":[4.0,8.75,4.125,8.875],"tintindex":0,"rotation":0,"texture":"#0"},"west":{"uv":[6.25,0.25,8.625,0.375],"tintindex":0,"rotation":0,"texture":"#0"},"up":{"uv":[5.5,8.375,5.375,6.0],"tintindex":0,"rotation":0,"texture":"#0"},"down":{"uv":[3.875,6.375,3.75,8.75],"tintindex":0,"rotation":0,"texture":"#0"}}},{"from":[7.4998,7.366667,-7.9562387],"to":[8.4998,7.616667,-7.4562387],"faces":{"east":{"uv":[2.75,9.125,2.8125,9.1875],"tintindex":0,"rotation":0,"texture":"#0"},"south":{"uv":[3.875,9.0,4.0,9.0625],"tintindex":0,"rotation":0,"texture":"#0"},"north":{"uv":[1.5,9.0,1.625,9.0625],"tintindex":0,"rotation":0,"texture":"#0"},"west":{"uv":[9.125,2.75,9.1875,2.8125],"tintindex":0,"rotation":0,"texture":"#0"},"up":{"uv":[4.25,9.0625,4.125,9.0],"tintindex":0,"rotation":0,"texture":"#0"},"down":{"uv":[9.125,5.25,9.0,5.3125],"tintindex":0,"rotation":0,"texture":"#0"}}},{"from":[6.9998,6.866667,-6.4562387],"to":[8.9998,8.866667,-4.4562387],"faces":{"east":{"uv":[8.25,5.875,8.5,6.125],"tintindex":0,"rotation":0,"texture":"#0"},"south":{"uv":[8.25,6.25,8.5,6.5],"tintindex":0,"rotation":0,"texture":"#0"},"north":{"uv":[8.25,3.625,8.5,3.875],"tintindex":0,"rotation":0,"texture":"#0"},"west":{"uv":[8.25,6.625,8.5,6.875],"tintindex":0,"rotation":0,"texture":"#0"},"up":{"uv":[8.5,7.25,8.25,7.0],"tintindex":0,"rotation":0,"texture":"#0"},"down":{"uv":[0.75,8.375,0.5,8.625],"tintindex":0,"rotation":0,"texture":"#0"}}},{"from":[8.4998,5.866667,-4.4562387],"to":[12.4998,9.866667,-4.4562387],"faces":{"south":{"uv":[7.375,3.0,6.875,3.5],"tintindex":0,"rotation":0,"texture":"#0"},"north":{"uv":[6.875,3.0,7.375,3.5],"tintindex":0,"rotation":0,"texture":"#0"}},"rotation":{"origin":[8.4998,7.866667,-4.4562387],"angle":-45.0,"axis":"y"}},{"from":[5.9998,8.366667,-4.4562387],"to":[9.9998,12.366667,-4.4562387],"faces":{"south":{"uv":[7.125,6.375,6.625,6.875],"tintindex":0,"rotation":0,"texture":"#0"},"north":{"uv":[6.625,6.375,7.125,6.875],"tintindex":0,"rotation":0,"texture":"#0"}},"rotation":{"origin":[7.9998,8.366667,-4.4562387],"angle":45.0,"axis":"x"}},{"from":[7.4998,7.616667,-7.9562387],"to":[7.7498,8.116667,-7.4562387],"faces":{"east":{"uv":[9.125,4.0,9.1875,4.0625],"tintindex":0,"rotation":0,"texture":"#0"},"south":{"uv":[9.125,4.25,9.1875,4.3125],"tintindex":0,"rotation":0,"texture":"#0"},"north":{"uv":[9.125,3.75,9.1875,3.8125],"tintindex":0,"rotation":0,"texture":"#0"},"west":{"uv":[4.375,9.125,4.4375,9.1875],"tintindex":0,"rotation":0,"texture":"#0"},"up":{"uv":[9.1875,4.5625,9.125,4.5],"tintindex":0,"rotation":0,"texture":"#0"},"down":{"uv":[4.6875,9.125,4.625,9.1875],"tintindex":0,"rotation":0,"texture":"#0"}}},{"from":[7.4998,8.116667,-7.9562387],"to":[8.4998,8.366667,-7.4562387],"faces":{"east":{"uv":[2.5,9.125,2.5625,9.1875],"tintindex":0,"rotation":0,"texture":"#0"},"south":{"uv":[9.0,0.75,9.125,0.8125],"tintindex":0,"rotation":0,"texture":"#0"},"north":{"uv":[0.75,9.0,0.875,9.0625],"tintindex":0,"rotation":0,"texture":"#0"},"west":{"uv":[9.125,2.5,9.1875,2.5625],"tintindex":0,"rotation":0,"texture":"#0"},"up":{"uv":[1.125,9.0625,1.0,9.0],"tintindex":0,"rotation":0,"texture":"#0"},"down":{"uv":[1.375,9.0,1.25,9.0625],"tintindex":0,"rotation":0,"texture":"#0"}}},{"from":[7.5048003,7.23032,-7.7844477],"to":[8.497801,8.23032,-6.2844477],"faces":{"east":{"uv":[8.625,7.0,8.8125,7.125],"tintindex":0,"rotation":0,"texture":"#0"},"south":{"uv":[1.875,8.875,2.0,9.0],"tintindex":0,"rotation":0,"texture":"#0"},"north":{"uv":[8.875,1.5,9.0,1.625],"tintindex":0,"rotation":0,"texture":"#0"},"west":{"uv":[7.625,8.625,7.8125,8.75],"tintindex":0,"rotation":0,"texture":"#0"},"up":{"uv":[8.125,8.8125,8.0,8.625],"tintindex":0,"rotation":0,"texture":"#0"},"down":{"uv":[8.75,8.125,8.625,8.3125],"tintindex":0,"rotation":0,"texture":"#0"}},"rotation":{"origin":[8.4998,7.48032,-7.2844477],"angle":22.5,"axis":"x"}},{"from":[7.4623003,7.3291664,6.5437613],"to":[8.5373,8.404167,9.543761],"faces":{"east":{"uv":[7.75,8.375,8.125,8.5],"tintindex":0,"rotation":0,"texture":"#0"},"south":{"uv":[8.875,2.5,9.0,2.625],"tintindex":0,"rotation":0,"texture":"#0"},"north":{"uv":[2.125,8.875,2.25,9.0],"tintindex":0,"rotation":0,"texture":"#0"},"west":{"uv":[8.375,7.875,8.75,8.0],"tintindex":0,"rotation":0,"texture":"#0"},"up":{"uv":[3.5,8.75,3.375,8.375],"tintindex":0,"rotation":0,"texture":"#0"},"down":{"uv":[8.5,8.125,8.375,8.5],"tintindex":0,"rotation":0,"texture":"#0"}}},{"from":[3.4998002,5.866667,-4.4562387],"to":[7.4998,9.866667,-4.4562387],"faces":{"south":{"uv":[7.375,1.75,6.875,2.25],"tintindex":0,"rotation":0,"texture":"#0"},"north":{"uv":[6.875,1.75,7.375,2.25],"tintindex":0,"rotation":0,"texture":"#0"}},"rotation":{"origin":[7.4998,7.866667,-4.4562387],"angle":45.0,"axis":"y"}},{"from":[7.5048003,7.5030136,-7.7844477],"to":[8.497801,8.503014,-6.2844477],"faces":{"east":{"uv":[8.625,5.25,8.8125,5.375],"tintindex":0,"rotation":0,"texture":"#0"},"south":{"uv":[8.875,1.25,9.0,1.375],"tintindex":0,"rotation":0,"texture":"#0"},"north":{"uv":[0.0,8.875,0.125,9.0],"tintindex":0,"rotation":0,"texture":"#0"},"west":{"uv":[8.625,6.375,8.8125,6.5],"tintindex":0,"rotation":0,"texture":"#0"},"up":{"uv":[6.5,8.8125,6.375,8.625],"tintindex":0,"rotation":0,"texture":"#0"},"down":{"uv":[8.75,6.625,8.625,6.8125],"tintindex":0,"rotation":0,"texture":"#0"}},"rotation":{"origin":[8.4998,8.253014,-7.2844477],"angle":-22.5,"axis":"x"}},{"from":[7.2498,7.116667,-2.4562387],"to":[8.7498,8.616667,0.54376125],"faces":{"east":{"uv":[0.0,8.25,0.375,8.4375],"tintindex":0,"rotation":0,"texture":"#0"},"south":{"uv":[8.5,4.625,8.6875,4.8125],"tintindex":0,"rotation":0,"texture":"#0"},"north":{"uv":[4.5,8.5,4.6875,8.6875],"tintindex":0,"rotation":0,"texture":"#0"},"west":{"uv":[8.25,0.5,8.625,0.6875],"tintindex":0,"rotation":0,"texture":"#0"},"up":{"uv":[5.1875,4.125,5.0,3.75],"tintindex":0,"rotation":0,"texture":"#0"},"down":{"uv":[5.5625,4.625,5.375,5.0],"tintindex":0,"rotation":0,"texture":"#0"}}},{"from":[5.9998,3.3666668,-4.4562387],"to":[9.9998,7.366667,-4.4562387],"faces":{"south":{"uv":[5.25,6.875,4.75,7.375],"tintindex":0,"rotation":0,"texture":"#0"},"north":{"uv":[4.75,6.875,5.25,7.375],"tintindex":0,"rotation":0,"texture":"#0"}},"rotation":{"origin":[7.9998,7.366667,-4.4562387],"angle":-45.0,"axis":"x"}},{"from":[8.2498,7.616667,-7.9562387],"to":[8.4998,8.116667,-7.4562387],"faces":{"east":{"uv":[9.125,3.0,9.1875,3.0625],"tintindex":0,"rotation":0,"texture":"#0"},"south":{"uv":[3.25,9.125,3.3125,9.1875],"tintindex":0,"rotation":0,"texture":"#0"},"north":{"uv":[3.0,9.125,3.0625,9.1875],"tintindex":0,"rotation":0,"texture":"#0"},"west":{"uv":[9.125,3.25,9.1875,3.3125],"tintindex":0,"rotation":0,"texture":"#0"},"up":{"uv":[3.5625,9.1875,3.5,9.125],"tintindex":0,"rotation":0,"texture":"#0"},"down":{"uv":[9.1875,3.5,9.125,3.5625],"tintindex":0,"rotation":0,"texture":"#0"}}}],"display":{"gui":{"rotation":[30,225,0]}}}