{"textures":{"2":"modelengine:entity/em_darklurker"},"elements":[{"from":[7.0,-8.672382,7.6686306],"to":[9.0,-6.6723833,9.668631],"faces":{"east":{"uv":[7.5,0.0,7.75,0.25],"tintindex":0,"rotation":0,"texture":"#2"},"south":{"uv":[7.5,2.625,7.75,2.875],"tintindex":0,"rotation":0,"texture":"#2"},"north":{"uv":[7.375,5.375,7.625,5.625],"tintindex":0,"rotation":0,"texture":"#2"},"west":{"uv":[7.5,3.0,7.75,3.25],"tintindex":0,"rotation":0,"texture":"#2"},"up":{"uv":[7.75,3.625,7.5,3.375],"tintindex":0,"rotation":0,"texture":"#2"},"down":{"uv":[4.625,7.5,4.375,7.75],"tintindex":0,"rotation":0,"texture":"#2"}}},{"from":[7.1,-8.333017,3.0692663],"to":[8.9,-1.5330178,4.869266],"faces":{"east":{"uv":[3.0,5.625,3.25,6.5],"tintindex":0,"rotation":0,"texture":"#2"},"south":{"uv":[5.625,3.0,5.875,3.875],"tintindex":0,"rotation":0,"texture":"#2"},"north":{"uv":[2.625,5.625,2.875,6.5],"tintindex":0,"rotation":0,"texture":"#2"},"west":{"uv":[4.125,5.625,4.375,6.5],"tintindex":0,"rotation":0,"texture":"#2"},"up":{"uv":[2.875,7.625,2.625,7.375],"tintindex":0,"rotation":0,"texture":"#2"},"down":{"uv":[5.375,7.375,5.125,7.625],"tintindex":0,"rotation":0,"texture":"#2"}},"rotation":{"origin":[8.0,4.3044815,6.4692664],"angle":-22.5,"axis":"x"}},{"from":[7.0,-1.6955185,2.9692664],"to":[9.0,2.3044815,5.969266],"faces":{"east":{"uv":[6.125,5.625,6.5,6.125],"tintindex":0,"rotation":0,"texture":"#2"},"south":{"uv":[6.5,6.25,6.75,6.75],"tintindex":0,"rotation":0,"texture":"#2"},"north":{"uv":[4.875,6.5,5.125,7.0],"tintindex":0,"rotation":0,"texture":"#2"},"west":{"uv":[6.25,0.0,6.625,0.5],"tintindex":0,"rotation":0,"texture":"#2"},"up":{"uv":[7.0,0.375,6.75,0.0],"tintindex":0,"rotation":0,"texture":"#2"},"down":{"uv":[7.0,2.625,6.75,3.0],"tintindex":0,"rotation":0,"texture":"#2"}},"rotation":{"origin":[8.0,4.3044815,6.4692664],"angle":-22.5,"axis":"x"}},{"from":[6.5,0.0,6.5],"to":[9.5,8.0,9.5],"faces":{"east":{"uv":[4.5,2.25,4.875,3.25],"tintindex":0,"rotation":0,"texture":"#2"},"south":{"uv":[3.0,4.5,3.375,5.5],"tintindex":0,"rotation":0,"texture":"#2"},"north":{"uv":[4.375,1.125,4.75,2.125],"tintindex":0,"rotation":0,"texture":"#2"},"west":{"uv":[4.5,3.375,4.875,4.375],"tintindex":0,"rotation":0,"texture":"#2"},"up":{"uv":[6.75,2.0,6.375,1.625],"tintindex":0,"rotation":0,"texture":"#2"},"down":{"uv":[6.75,2.125,6.375,2.5],"tintindex":0,"rotation":0,"texture":"#2"}},"rotation":{"origin":[8.0,8.0,8.0],"angle":22.5,"axis":"x"}}],"display":{"gui":{"rotation":[30,225,0]}}}